face_extract-0.0.5.dist-info/METADATA
face_extract-0.0.5.dist-info/RECORD
face_extract-0.0.5.dist-info/WHEEL
face_extract-0.0.5.dist-info/top_level.txt
face_extractor/__init__.py
face_extractor/face_extract.py
