Metadata-Version: 2.1
Name: face-extract
Version: 0.0.5
Summary: You can extract face in user identity image
Home-page: UNKNOWN
Author: Anupam Jain
Author-email: anupam124jain@gmail.com
License: UNKNOWN
Platform: UNKNOWN
Classifier: Programming Language :: Python :: 3
Classifier: License :: OSI Approved :: MIT License
Classifier: Operating System :: OS Independent
Requires-Dist: opencv-python (==3.4.2.17)
